cap/__init__.py
cap/core.py
cap-0.1.4.dist-info/LICENSE
cap-0.1.4.dist-info/METADATA
cap-0.1.4.dist-info/WHEEL
cap-0.1.4.dist-info/RECORD
