Metadata-Version: 2.1
Name: cap
Version: 0.1.4
Summary: Cap: lightweight package for use network captures
License: MIT
Author: Netanel Revah
Author-email: netanelrevah@outlook.com
Requires-Python: >=3.10,<4.0
Classifier: License :: OSI Approved :: MIT License
Classifier: Programming Language :: Python :: 3
Classifier: Programming Language :: Python :: 3.10
Classifier: Programming Language :: Python :: 3.11
Requires-Dist: bidict (>=0.22.1,<0.23.0)
